{"nodes": [{"id": "pricing_page", "label": "Pricing & Membership Page (pricing.html)", "file_type": "code", "source_file": "pricing.html", "source_location": null, "source_url": null, "captured_at": null, "author": null, "contributor": null}], "edges": [{"source": "pricing_page", "target": "role_gratis", "relation": "references", "confidence": "EXTRACTED", "confidence_score": 1.0, "source_file": "pricing.html", "source_location": "line 8", "weight": 1.0}, {"source": "pricing_page", "target": "role_basic", "relation": "references", "confidence": "EXTRACTED", "confidence_score": 1.0, "source_file": "pricing.html", "source_location": "line 8", "weight": 1.0}, {"source": "pricing_page", "target": "role_premium", "relation": "references", "confidence": "EXTRACTED", "confidence_score": 1.0, "source_file": "pricing.html", "source_location": "line 8", "weight": 1.0}, {"source": "pricing_page", "target": "shared_js", "relation": "references", "confidence": "EXTRACTED", "confidence_score": 1.0, "source_file": "pricing.html", "source_location": "line 13", "weight": 1.0}], "hyperedges": []}